semarchy_xdi_runtime_client/cli/__init__.py
semarchy_xdi_runtime_client/cli/main.py
semarchy_xdi_runtime_client/client/__init__.py
semarchy_xdi_runtime_client/client/client.py
semarchy_xdi_runtime_client/client/enum.py
semarchy_xdi_runtime_client/client/exceptions.py
semarchy_xdi_runtime_client/client/helpers.py
semarchy_xdi_runtime_client-0.2.3.dist-info/LICENSE.md
semarchy_xdi_runtime_client-0.2.3.dist-info/METADATA
semarchy_xdi_runtime_client-0.2.3.dist-info/WHEEL
semarchy_xdi_runtime_client-0.2.3.dist-info/entry_points.txt
semarchy_xdi_runtime_client-0.2.3.dist-info/top_level.txt
semarchy_xdi_runtime_client-0.2.3.dist-info/RECORD
